pYTerm/__init__.py
pYTerm/pYTerm.py
pYTerm/tools.py
p_yt_erm-0.5.post1.dist-info/LICENSE
p_yt_erm-0.5.post1.dist-info/METADATA
p_yt_erm-0.5.post1.dist-info/WHEEL
p_yt_erm-0.5.post1.dist-info/entry_points.txt
p_yt_erm-0.5.post1.dist-info/top_level.txt
p_yt_erm-0.5.post1.dist-info/RECORD
