Metadata-Version: 2.1
Name: p-yt-erm
Version: 0.5.post1
Summary: Easy to use youtube music streamer command line tool written in python3
Home-page: https://gitlab.com/mocchapi/pyterminal/
Author: Anne & Lynice
Maintainer: Alex Technically
Maintainer-email: alex@2a03.party
License: UNKNOWN
Platform: UNKNOWN
Classifier: Programming Language :: Python :: 3
Classifier: Operating System :: OS Independent
Classifier: Topic :: Multimedia :: Sound/Audio :: Players
Classifier: Development Status :: 4 - Beta
Requires-Python: >=3.8
License-File: LICENSE
Requires-Dist: python-vlc
Requires-Dist: pafy
Requires-Dist: pypresence
Requires-Dist: feedparser
Requires-Dist: youtube-search-python
Requires-Dist: youtube-dl
